mcp_fred/__init__.py
mcp_fred/__main__.py
mcp_fred/config.py
mcp_fred/server.py
mcp_fred/api/__init__.py
mcp_fred/api/client.py
mcp_fred/api/endpoints/__init__.py
mcp_fred/api/endpoints/category.py
mcp_fred/api/endpoints/maps.py
mcp_fred/api/endpoints/release.py
mcp_fred/api/endpoints/series.py
mcp_fred/api/endpoints/source.py
mcp_fred/api/endpoints/tag.py
mcp_fred/api/models/__init__.py
mcp_fred/api/models/responses.py
mcp_fred/tools/__init__.py
mcp_fred/tools/_common.py
mcp_fred/tools/category.py
mcp_fred/tools/job_cancel.py
mcp_fred/tools/job_list.py
mcp_fred/tools/job_status.py
mcp_fred/tools/maps.py
mcp_fred/tools/project_create.py
mcp_fred/tools/project_list.py
mcp_fred/tools/release.py
mcp_fred/tools/series.py
mcp_fred/tools/source.py
mcp_fred/tools/tag.py
mcp_fred/transports/__init__.py
mcp_fred/transports/stdio.py
mcp_fred/utils/__init__.py
mcp_fred/utils/background_worker.py
mcp_fred/utils/file_writer.py
mcp_fred/utils/job_manager.py
mcp_fred/utils/json_to_csv.py
mcp_fred/utils/output_handler.py
mcp_fred/utils/path_resolver.py
mcp_fred/utils/token_estimator.py
mcp_fred-0.1.0.dist-info/METADATA
mcp_fred-0.1.0.dist-info/WHEEL
mcp_fred-0.1.0.dist-info/top_level.txt
mcp_fred-0.1.0.dist-info/RECORD
