Metadata-Version: 2.4
Name: mcp-fred
Version: 0.1.0
Summary: Model Context Protocol server for Federal Reserve Economic Data (FRED) API
Author-email: cfdude <cfdude@users.noreply.github.com>
License-Expression: MIT
Project-URL: Homepage, https://github.com/cfdude/mcp-fred
Project-URL: Documentation, https://github.com/cfdude/mcp-fred/blob/main/README.md
Project-URL: Repository, https://github.com/cfdude/mcp-fred
Project-URL: Issues, https://github.com/cfdude/mcp-fred/issues
Project-URL: Changelog, https://github.com/cfdude/mcp-fred/blob/main/CHANGELOG.md
Keywords: mcp,model-context-protocol,fred,federal-reserve,economic-data,api,claude
Classifier: Development Status :: 3 - Alpha
Classifier: Intended Audience :: Developers
Classifier: Programming Language :: Python :: 3
Classifier: Programming Language :: Python :: 3.11
Classifier: Programming Language :: Python :: 3.12
Classifier: Topic :: Software Development :: Libraries :: Python Modules
Requires-Python: >=3.11
Requires-Dist: fastapi<1.0.0,>=0.100.0
Requires-Dist: httpx<1.0.0,>=0.24.0
Requires-Dist: pydantic<3.0.0,>=2.0.0
Requires-Dist: python-dotenv>=1.0.0
Requires-Dist: tiktoken<1.0.0,>=0.5.0
Provides-Extra: dev
Requires-Dist: ruff>=0.1.0; extra == "dev"
Requires-Dist: pytest<8.0.0,>=7.0.0; extra == "dev"
Requires-Dist: pytest-asyncio>=0.21.0; extra == "dev"
Requires-Dist: pytest-cov>=4.0.0; extra == "dev"
Requires-Dist: respx>=0.20.0; extra == "dev"
